{"cameraMode":{"drawMode":0,"name":"Shaded","section":"Shading Mode"},"sceneLighting":true,"audioPlay":false,"sceneViewState":{"showFog":true,"showMaterialUpdate":false,"showSkybox":true,"showFlares":true,"showImageEffects":true,"showParticleSystems":true},"in2DMode":false,"pivot":{"x":-4.558351516723633,"y":6.170273780822754,"z":4.327131748199463},"rotation":{"x":-0.40942513942718508,"y":-0.590514063835144,"z":0.48619285225868227,"w":-0.4972763955593109},"size":5.629344463348389,"orthographic":false}